{
  "pack": {
    "_id": "weeds",
    "name": "Weeds"
  },
  "name": "Funnel Weed",
  "tags": [
    "cotula turbinata",
    "buttonweed",
    "archviz"
  ],
  "models": [
    {
      "mimeType": "application/x-abc",
      "lod": 0,
      "contentLength": 52096,
      "uri": "Var1/Var1_LOD0.abc",
      "variation": 1,
      "type": "lod"
    },
    {
      "mimeType": "application/x-fbx",
      "lod": 0,
      "contentLength": 52784,
      "uri": "Var1/Var1_LOD0.fbx",
      "variation": 1,
      "type": "lod"
    },
    {
      "mimeType": "application/x-abc",
      "lod": 1,
      "contentLength": 23064,
      "uri": "Var1/Var1_LOD1.abc",
      "variation": 1,
      "type": "lod"
    },
    {
      "mimeType": "application/x-fbx",
      "lod": 1,
      "contentLength": 36208,
      "uri": "Var1/Var1_LOD1.fbx",
      "variation": 1,
      "type": "lod"
    },
    {
      "mimeType": "application/x-abc",
      "lod": 2,
      "contentLength": 15016,
      "uri": "Var1/Var1_LOD2.abc",
      "variation": 1,
      "type": "lod"
    },
    {
      "mimeType": "application/x-fbx",
      "lod": 2,
      "contentLength": 35040,
      "uri": "Var1/Var1_LOD2.fbx",
      "variation": 1,
      "type": "lod"
    },
    {
      "mimeType": "application/x-abc",
      "lod": 3,
      "contentLength": 4260,
      "uri": "Var1/Var1_LOD3.abc",
      "variation": 1,
      "type": "lod"
    },
    {
      "mimeType": "application/x-fbx",
      "lod": 3,
      "contentLength": 24976,
      "uri": "Var1/Var1_LOD3.fbx",
      "variation": 1,
      "type": "lod"
    },
    {
      "mimeType": "application/x-abc",
      "lod": 0,
      "contentLength": 39244,
      "uri": "Var2/Var2_LOD0.abc",
      "variation": 2,
      "type": "lod"
    },
    {
      "mimeType": "application/x-fbx",
      "lod": 0,
      "contentLength": 44784,
      "uri": "Var2/Var2_LOD0.fbx",
      "variation": 2,
      "type": "lod"
    },
    {
      "mimeType": "application/x-abc",
      "lod": 1,
      "contentLength": 17472,
      "uri": "Var2/Var2_LOD1.abc",
      "variation": 2,
      "type": "lod"
    },
    {
      "mimeType": "application/x-fbx",
      "lod": 1,
      "contentLength": 32736,
      "uri": "Var2/Var2_LOD1.fbx",
      "variation": 2,
      "type": "lod"
    },
    {
      "mimeType": "application/x-abc",
      "lod": 2,
      "contentLength": 10688,
      "uri": "Var2/Var2_LOD2.abc",
      "variation": 2,
      "type": "lod"
    },
    {
      "mimeType": "application/x-fbx",
      "lod": 2,
      "contentLength": 30784,
      "uri": "Var2/Var2_LOD2.fbx",
      "variation": 2,
      "type": "lod"
    },
    {
      "mimeType": "application/x-abc",
      "lod": 3,
      "contentLength": 3900,
      "uri": "Var2/Var2_LOD3.abc",
      "variation": 2,
      "type": "lod"
    },
    {
      "mimeType": "application/x-fbx",
      "lod": 3,
      "contentLength": 23744,
      "uri": "Var2/Var2_LOD3.fbx",
      "variation": 2,
      "type": "lod"
    },
    {
      "mimeType": "application/x-abc",
      "lod": 0,
      "contentLength": 26420,
      "uri": "Var3/Var3_LOD0.abc",
      "variation": 3,
      "type": "lod"
    },
    {
      "mimeType": "application/x-fbx",
      "lod": 0,
      "contentLength": 36736,
      "uri": "Var3/Var3_LOD0.fbx",
      "variation": 3,
      "type": "lod"
    },
    {
      "mimeType": "application/x-abc",
      "lod": 1,
      "contentLength": 12384,
      "uri": "Var3/Var3_LOD1.abc",
      "variation": 3,
      "type": "lod"
    },
    {
      "mimeType": "application/x-fbx",
      "lod": 1,
      "contentLength": 32336,
      "uri": "Var3/Var3_LOD1.fbx",
      "variation": 3,
      "type": "lod"
    },
    {
      "mimeType": "application/x-abc",
      "lod": 2,
      "contentLength": 8152,
      "uri": "Var3/Var3_LOD2.abc",
      "variation": 3,
      "type": "lod"
    },
    {
      "mimeType": "application/x-fbx",
      "lod": 2,
      "contentLength": 28976,
      "uri": "Var3/Var3_LOD2.fbx",
      "variation": 3,
      "type": "lod"
    },
    {
      "mimeType": "application/x-abc",
      "lod": 3,
      "contentLength": 3900,
      "uri": "Var3/Var3_LOD3.abc",
      "variation": 3,
      "type": "lod"
    },
    {
      "mimeType": "application/x-fbx",
      "lod": 3,
      "contentLength": 23744,
      "uri": "Var3/Var3_LOD3.fbx",
      "variation": 3,
      "type": "lod"
    },
    {
      "mimeType": "application/x-abc",
      "lod": 0,
      "contentLength": 23760,
      "uri": "Var4/Var4_LOD0.abc",
      "variation": 4,
      "type": "lod"
    },
    {
      "mimeType": "application/x-fbx",
      "lod": 0,
      "contentLength": 34928,
      "uri": "Var4/Var4_LOD0.fbx",
      "variation": 4,
      "type": "lod"
    },
    {
      "mimeType": "application/x-abc",
      "lod": 1,
      "contentLength": 11620,
      "uri": "Var4/Var4_LOD1.abc",
      "variation": 4,
      "type": "lod"
    },
    {
      "mimeType": "application/x-fbx",
      "lod": 1,
      "contentLength": 31296,
      "uri": "Var4/Var4_LOD1.fbx",
      "variation": 4,
      "type": "lod"
    },
    {
      "mimeType": "application/x-abc",
      "lod": 2,
      "contentLength": 7824,
      "uri": "Var4/Var4_LOD2.abc",
      "variation": 4,
      "type": "lod"
    },
    {
      "mimeType": "application/x-fbx",
      "lod": 2,
      "contentLength": 28512,
      "uri": "Var4/Var4_LOD2.fbx",
      "variation": 4,
      "type": "lod"
    },
    {
      "mimeType": "application/x-abc",
      "lod": 3,
      "contentLength": 3900,
      "uri": "Var4/Var4_LOD3.abc",
      "variation": 4,
      "type": "lod"
    },
    {
      "mimeType": "application/x-fbx",
      "lod": 3,
      "contentLength": 24224,
      "uri": "Var4/Var4_LOD3.fbx",
      "variation": 4,
      "type": "lod"
    },
    {
      "mimeType": "application/x-abc",
      "lod": 0,
      "contentLength": 13608,
      "uri": "Var5/Var5_LOD0.abc",
      "variation": 5,
      "type": "lod"
    },
    {
      "mimeType": "application/x-fbx",
      "lod": 0,
      "contentLength": 31376,
      "uri": "Var5/Var5_LOD0.fbx",
      "variation": 5,
      "type": "lod"
    },
    {
      "mimeType": "application/x-abc",
      "lod": 1,
      "contentLength": 8356,
      "uri": "Var5/Var5_LOD1.abc",
      "variation": 5,
      "type": "lod"
    },
    {
      "mimeType": "application/x-fbx",
      "lod": 1,
      "contentLength": 29456,
      "uri": "Var5/Var5_LOD1.fbx",
      "variation": 5,
      "type": "lod"
    },
    {
      "mimeType": "application/x-abc",
      "lod": 2,
      "contentLength": 6120,
      "uri": "Var5/Var5_LOD2.abc",
      "variation": 5,
      "type": "lod"
    },
    {
      "mimeType": "application/x-fbx",
      "lod": 2,
      "contentLength": 27408,
      "uri": "Var5/Var5_LOD2.fbx",
      "variation": 5,
      "type": "lod"
    },
    {
      "mimeType": "application/x-abc",
      "lod": 3,
      "contentLength": 3812,
      "uri": "Var5/Var5_LOD3.abc",
      "variation": 5,
      "type": "lod"
    },
    {
      "mimeType": "application/x-fbx",
      "lod": 3,
      "contentLength": 23552,
      "uri": "Var5/Var5_LOD3.fbx",
      "variation": 5,
      "type": "lod"
    },
    {
      "mimeType": "application/x-abc",
      "lod": 0,
      "contentLength": 12376,
      "uri": "Var6/Var6_LOD0.abc",
      "variation": 6,
      "type": "lod"
    },
    {
      "mimeType": "application/x-fbx",
      "lod": 0,
      "contentLength": 32832,
      "uri": "Var6/Var6_LOD0.fbx",
      "variation": 6,
      "type": "lod"
    },
    {
      "mimeType": "application/x-abc",
      "lod": 1,
      "contentLength": 7952,
      "uri": "Var6/Var6_LOD1.abc",
      "variation": 6,
      "type": "lod"
    },
    {
      "mimeType": "application/x-fbx",
      "lod": 1,
      "contentLength": 28688,
      "uri": "Var6/Var6_LOD1.fbx",
      "variation": 6,
      "type": "lod"
    },
    {
      "mimeType": "application/x-abc",
      "lod": 2,
      "contentLength": 5912,
      "uri": "Var6/Var6_LOD2.abc",
      "variation": 6,
      "type": "lod"
    },
    {
      "mimeType": "application/x-fbx",
      "lod": 2,
      "contentLength": 27008,
      "uri": "Var6/Var6_LOD2.fbx",
      "variation": 6,
      "type": "lod"
    },
    {
      "mimeType": "application/x-abc",
      "lod": 3,
      "contentLength": 3692,
      "uri": "Var6/Var6_LOD3.abc",
      "variation": 6,
      "type": "lod"
    },
    {
      "mimeType": "application/x-fbx",
      "lod": 3,
      "contentLength": 23312,
      "uri": "Var6/Var6_LOD3.fbx",
      "variation": 6,
      "type": "lod"
    },
    {
      "mimeType": "application/x-abc",
      "lod": 0,
      "contentLength": 15512,
      "uri": "Var7/Var7_LOD0.abc",
      "variation": 7,
      "type": "lod"
    },
    {
      "mimeType": "application/x-fbx",
      "lod": 0,
      "contentLength": 33296,
      "uri": "Var7/Var7_LOD0.fbx",
      "variation": 7,
      "type": "lod"
    },
    {
      "mimeType": "application/x-abc",
      "lod": 1,
      "contentLength": 12016,
      "uri": "Var7/Var7_LOD1.abc",
      "variation": 7,
      "type": "lod"
    },
    {
      "mimeType": "application/x-fbx",
      "lod": 1,
      "contentLength": 31184,
      "uri": "Var7/Var7_LOD1.fbx",
      "variation": 7,
      "type": "lod"
    },
    {
      "mimeType": "application/x-abc",
      "lod": 2,
      "contentLength": 8304,
      "uri": "Var7/Var7_LOD2.abc",
      "variation": 7,
      "type": "lod"
    },
    {
      "mimeType": "application/x-fbx",
      "lod": 2,
      "contentLength": 29296,
      "uri": "Var7/Var7_LOD2.fbx",
      "variation": 7,
      "type": "lod"
    },
    {
      "mimeType": "application/x-abc",
      "lod": 3,
      "contentLength": 3572,
      "uri": "Var7/Var7_LOD3.abc",
      "variation": 7,
      "type": "lod"
    },
    {
      "mimeType": "application/x-fbx",
      "lod": 3,
      "contentLength": 23056,
      "uri": "Var7/Var7_LOD3.fbx",
      "variation": 7,
      "type": "lod"
    }
  ],
  "billboards": [
    {
      "mimeType": "image/x-exr",
      "bitDepth": 32,
      "name": "AO",
      "resolution": "1024x1024",
      "contentLength": 3558905,
      "colorSpace": "sRGB",
      "uri": "Textures/Billboard/Billboard_1K_AO.exr",
      "asset": "ti2haioia",
      "physicalSize": "1x1",
      "type": "ao",
      "averageColor": "#000000"
    },
    {
      "mimeType": "image/jpeg",
      "bitDepth": 8,
      "name": "AO",
      "resolution": "1024x1024",
      "contentLength": 338755,
      "colorSpace": "sRGB",
      "uri": "Textures/Billboard/Billboard_1K_AO.jpg",
      "asset": "ti2haioia",
      "physicalSize": "1x1",
      "type": "ao",
      "averageColor": "#000000"
    },
    {
      "mimeType": "image/x-exr",
      "bitDepth": 16,
      "name": "Albedo",
      "resolution": "1024x1024",
      "contentLength": 10506924,
      "colorSpace": "sRGB",
      "uri": "Textures/Billboard/Billboard_1K_Albedo.exr",
      "asset": "ti2haioia",
      "physicalSize": "1x1",
      "type": "albedo",
      "averageColor": "#000000"
    },
    {
      "mimeType": "image/jpeg",
      "bitDepth": 8,
      "name": "Albedo",
      "resolution": "1024x1024",
      "contentLength": 506949,
      "colorSpace": "sRGB",
      "uri": "Textures/Billboard/Billboard_1K_Albedo.jpg",
      "asset": "ti2haioia",
      "physicalSize": "1x1",
      "type": "albedo",
      "averageColor": "#000000"
    },
    {
      "mimeType": "image/x-exr",
      "bitDepth": 32,
      "name": "Bump",
      "resolution": "1024x1024",
      "contentLength": 1783669,
      "colorSpace": "Linear",
      "uri": "Textures/Billboard/Billboard_1K_Bump.exr",
      "asset": "ti2haioia",
      "physicalSize": "1x1",
      "type": "bump",
      "averageColor": "#808080"
    },
    {
      "mimeType": "image/jpeg",
      "bitDepth": 8,
      "name": "Bump",
      "resolution": "1024x1024",
      "contentLength": 322784,
      "colorSpace": "Linear",
      "uri": "Textures/Billboard/Billboard_1K_Bump.jpg",
      "asset": "ti2haioia",
      "physicalSize": "1x1",
      "type": "bump",
      "averageColor": "#808080"
    },
    {
      "mimeType": "image/x-exr",
      "bitDepth": 32,
      "name": "Cavity",
      "resolution": "1024x1024",
      "contentLength": 3435177,
      "colorSpace": "sRGB",
      "uri": "Textures/Billboard/Billboard_1K_Cavity.exr",
      "asset": "ti2haioia",
      "physicalSize": "1x1",
      "type": "cavity",
      "averageColor": "#000000"
    },
    {
      "mimeType": "image/jpeg",
      "bitDepth": 8,
      "name": "Cavity",
      "resolution": "1024x1024",
      "contentLength": 286113,
      "colorSpace": "sRGB",
      "uri": "Textures/Billboard/Billboard_1K_Cavity.jpg",
      "asset": "ti2haioia",
      "physicalSize": "1x1",
      "type": "cavity",
      "averageColor": "#000000"
    },
    {
      "mimeType": "image/x-exr",
      "bitDepth": 32,
      "name": "Displacement",
      "resolution": "1024x1024",
      "contentLength": 1483786,
      "colorSpace": "Linear",
      "uri": "Textures/Billboard/Billboard_1K_Displacement.exr",
      "asset": "ti2haioia",
      "physicalSize": "1x1",
      "type": "displacement",
      "averageColor": "#000000"
    },
    {
      "mimeType": "image/jpeg",
      "bitDepth": 8,
      "name": "Displacement",
      "resolution": "1024x1024",
      "contentLength": 341744,
      "colorSpace": "Linear",
      "uri": "Textures/Billboard/Billboard_1K_Displacement.jpg",
      "asset": "ti2haioia",
      "physicalSize": "1x1",
      "type": "displacement",
      "averageColor": "#000000"
    },
    {
      "mimeType": "image/x-exr",
      "bitDepth": 32,
      "name": "Gloss",
      "resolution": "1024x1024",
      "contentLength": 3817000,
      "colorSpace": "Linear",
      "uri": "Textures/Billboard/Billboard_1K_Gloss.exr",
      "asset": "ti2haioia",
      "physicalSize": "1x1",
      "type": "gloss",
      "averageColor": "#000000"
    },
    {
      "mimeType": "image/jpeg",
      "bitDepth": 8,
      "name": "Gloss",
      "resolution": "1024x1024",
      "contentLength": 305587,
      "colorSpace": "Linear",
      "uri": "Textures/Billboard/Billboard_1K_Gloss.jpg",
      "asset": "ti2haioia",
      "physicalSize": "1x1",
      "type": "gloss",
      "averageColor": "#000000"
    },
    {
      "mimeType": "image/x-exr",
      "bitDepth": 16,
      "name": "Normal",
      "resolution": "1024x1024",
      "contentLength": 10410449,
      "colorSpace": "Linear",
      "uri": "Textures/Billboard/Billboard_1K_Normal.exr",
      "asset": "ti2haioia",
      "physicalSize": "1x1",
      "type": "normal",
      "averageColor": "#000000"
    },
    {
      "mimeType": "image/jpeg",
      "bitDepth": 8,
      "name": "Normal",
      "resolution": "1024x1024",
      "contentLength": 877243,
      "colorSpace": "Linear",
      "uri": "Textures/Billboard/Billboard_1K_Normal.jpg",
      "asset": "ti2haioia",
      "physicalSize": "1x1",
      "type": "normal",
      "averageColor": "#000000"
    },
    {
      "mimeType": "image/x-exr",
      "bitDepth": 32,
      "name": "Opacity",
      "resolution": "1024x1024",
      "contentLength": 1643020,
      "colorSpace": "Linear",
      "uri": "Textures/Billboard/Billboard_1K_Opacity.exr",
      "asset": "ti2haioia",
      "physicalSize": "1x1",
      "type": "opacity",
      "averageColor": "#000000"
    },
    {
      "mimeType": "image/jpeg",
      "bitDepth": 8,
      "name": "Opacity",
      "resolution": "1024x1024",
      "contentLength": 384681,
      "colorSpace": "Linear",
      "uri": "Textures/Billboard/Billboard_1K_Opacity.jpg",
      "asset": "ti2haioia",
      "physicalSize": "1x1",
      "type": "opacity",
      "averageColor": "#000000"
    },
    {
      "mimeType": "image/x-exr",
      "bitDepth": 32,
      "name": "Roughness",
      "resolution": "1024x1024",
      "contentLength": 3508815,
      "colorSpace": "Linear",
      "uri": "Textures/Billboard/Billboard_1K_Roughness.exr",
      "asset": "ti2haioia",
      "physicalSize": "1x1",
      "type": "roughness",
      "averageColor": "#FFFFFF"
    },
    {
      "mimeType": "image/jpeg",
      "bitDepth": 8,
      "name": "Roughness",
      "resolution": "1024x1024",
      "contentLength": 295485,
      "colorSpace": "Linear",
      "uri": "Textures/Billboard/Billboard_1K_Roughness.jpg",
      "asset": "ti2haioia",
      "physicalSize": "1x1",
      "type": "roughness",
      "averageColor": "#FFFFFF"
    },
    {
      "mimeType": "image/x-exr",
      "bitDepth": 16,
      "name": "Specular",
      "resolution": "1024x1024",
      "contentLength": 9320966,
      "colorSpace": "sRGB",
      "uri": "Textures/Billboard/Billboard_1K_Specular.exr",
      "asset": "ti2haioia",
      "physicalSize": "1x1",
      "type": "specular",
      "averageColor": "#000000"
    },
    {
      "mimeType": "image/jpeg",
      "bitDepth": 8,
      "name": "Specular",
      "resolution": "1024x1024",
      "contentLength": 184697,
      "colorSpace": "sRGB",
      "uri": "Textures/Billboard/Billboard_1K_Specular.jpg",
      "asset": "ti2haioia",
      "physicalSize": "1x1",
      "type": "specular",
      "averageColor": "#000000"
    },
    {
      "mimeType": "image/x-exr",
      "bitDepth": 16,
      "name": "Translucency",
      "resolution": "1024x1024",
      "contentLength": 11054123,
      "colorSpace": "sRGB",
      "uri": "Textures/Billboard/Billboard_1K_Translucency.exr",
      "asset": "ti2haioia",
      "physicalSize": "1x1",
      "type": "translucency",
      "averageColor": "#000000"
    },
    {
      "mimeType": "image/jpeg",
      "bitDepth": 8,
      "name": "Translucency",
      "resolution": "1024x1024",
      "contentLength": 606875,
      "colorSpace": "sRGB",
      "uri": "Textures/Billboard/Billboard_1K_Translucency.jpg",
      "asset": "ti2haioia",
      "physicalSize": "1x1",
      "type": "translucency",
      "averageColor": "#000000"
    },
    {
      "mimeType": "image/x-exr",
      "bitDepth": 32,
      "name": "AO",
      "resolution": "2048x2048",
      "contentLength": 12744687,
      "colorSpace": "sRGB",
      "uri": "Textures/Billboard/Billboard_2K_AO.exr",
      "asset": "ti2haioia",
      "physicalSize": "1x1",
      "type": "ao",
      "averageColor": "#000000"
    },
    {
      "mimeType": "image/jpeg",
      "bitDepth": 8,
      "name": "AO",
      "resolution": "2048x2048",
      "contentLength": 991722,
      "colorSpace": "sRGB",
      "uri": "Textures/Billboard/Billboard_2K_AO.jpg",
      "asset": "ti2haioia",
      "physicalSize": "1x1",
      "type": "ao",
      "averageColor": "#000000"
    },
    {
      "mimeType": "image/x-exr",
      "bitDepth": 16,
      "name": "Albedo",
      "resolution": "2048x2048",
      "contentLength": 37739250,
      "colorSpace": "sRGB",
      "uri": "Textures/Billboard/Billboard_2K_Albedo.exr",
      "asset": "ti2haioia",
      "physicalSize": "1x1",
      "type": "albedo",
      "averageColor": "#000000"
    },
    {
      "mimeType": "image/jpeg",
      "bitDepth": 8,
      "name": "Albedo",
      "resolution": "2048x2048",
      "contentLength": 1321882,
      "colorSpace": "sRGB",
      "uri": "Textures/Billboard/Billboard_2K_Albedo.jpg",
      "asset": "ti2haioia",
      "physicalSize": "1x1",
      "type": "albedo",
      "averageColor": "#000000"
    },
    {
      "mimeType": "image/x-exr",
      "bitDepth": 32,
      "name": "Bump",
      "resolution": "2048x2048",
      "contentLength": 6724104,
      "colorSpace": "Linear",
      "uri": "Textures/Billboard/Billboard_2K_Bump.exr",
      "asset": "ti2haioia",
      "physicalSize": "1x1",
      "type": "bump",
      "averageColor": "#808080"
    },
    {
      "mimeType": "image/jpeg",
      "bitDepth": 8,
      "name": "Bump",
      "resolution": "2048x2048",
      "contentLength": 920366,
      "colorSpace": "Linear",
      "uri": "Textures/Billboard/Billboard_2K_Bump.jpg",
      "asset": "ti2haioia",
      "physicalSize": "1x1",
      "type": "bump",
      "averageColor": "#808080"
    },
    {
      "mimeType": "image/x-exr",
      "bitDepth": 32,
      "name": "Cavity",
      "resolution": "2048x2048",
      "contentLength": 12289232,
      "colorSpace": "sRGB",
      "uri": "Textures/Billboard/Billboard_2K_Cavity.exr",
      "asset": "ti2haioia",
      "physicalSize": "1x1",
      "type": "cavity",
      "averageColor": "#000000"
    },
    {
      "mimeType": "image/jpeg",
      "bitDepth": 8,
      "name": "Cavity",
      "resolution": "2048x2048",
      "contentLength": 840024,
      "colorSpace": "sRGB",
      "uri": "Textures/Billboard/Billboard_2K_Cavity.jpg",
      "asset": "ti2haioia",
      "physicalSize": "1x1",
      "type": "cavity",
      "averageColor": "#000000"
    },
    {
      "mimeType": "image/x-exr",
      "bitDepth": 32,
      "name": "Displacement",
      "resolution": "2048x2048",
      "contentLength": 5250355,
      "colorSpace": "Linear",
      "uri": "Textures/Billboard/Billboard_2K_Displacement.exr",
      "asset": "ti2haioia",
      "physicalSize": "1x1",
      "type": "displacement",
      "averageColor": "#000000"
    },
    {
      "mimeType": "image/jpeg",
      "bitDepth": 8,
      "name": "Displacement",
      "resolution": "2048x2048",
      "contentLength": 929062,
      "colorSpace": "Linear",
      "uri": "Textures/Billboard/Billboard_2K_Displacement.jpg",
      "asset": "ti2haioia",
      "physicalSize": "1x1",
      "type": "displacement",
      "averageColor": "#000000"
    },
    {
      "mimeType": "image/x-exr",
      "bitDepth": 32,
      "name": "Gloss",
      "resolution": "2048x2048",
      "contentLength": 13779043,
      "colorSpace": "Linear",
      "uri": "Textures/Billboard/Billboard_2K_Gloss.exr",
      "asset": "ti2haioia",
      "physicalSize": "1x1",
      "type": "gloss",
      "averageColor": "#000000"
    },
    {
      "mimeType": "image/jpeg",
      "bitDepth": 8,
      "name": "Gloss",
      "resolution": "2048x2048",
      "contentLength": 875872,
      "colorSpace": "Linear",
      "uri": "Textures/Billboard/Billboard_2K_Gloss.jpg",
      "asset": "ti2haioia",
      "physicalSize": "1x1",
      "type": "gloss",
      "averageColor": "#000000"
    },
    {
      "mimeType": "image/x-exr",
      "bitDepth": 16,
      "name": "Normal",
      "resolution": "2048x2048",
      "contentLength": 37366179,
      "colorSpace": "Linear",
      "uri": "Textures/Billboard/Billboard_2K_Normal.exr",
      "asset": "ti2haioia",
      "physicalSize": "1x1",
      "type": "normal",
      "averageColor": "#000000"
    },
    {
      "mimeType": "image/jpeg",
      "bitDepth": 8,
      "name": "Normal",
      "resolution": "2048x2048",
      "contentLength": 2386485,
      "colorSpace": "Linear",
      "uri": "Textures/Billboard/Billboard_2K_Normal.jpg",
      "asset": "ti2haioia",
      "physicalSize": "1x1",
      "type": "normal",
      "averageColor": "#000000"
    },
    {
      "mimeType": "image/x-exr",
      "bitDepth": 32,
      "name": "Opacity",
      "resolution": "2048x2048",
      "contentLength": 5002718,
      "colorSpace": "Linear",
      "uri": "Textures/Billboard/Billboard_2K_Opacity.exr",
      "asset": "ti2haioia",
      "physicalSize": "1x1",
      "type": "opacity",
      "averageColor": "#000000"
    },
    {
      "mimeType": "image/jpeg",
      "bitDepth": 8,
      "name": "Opacity",
      "resolution": "2048x2048",
      "contentLength": 1007378,
      "colorSpace": "Linear",
      "uri": "Textures/Billboard/Billboard_2K_Opacity.jpg",
      "asset": "ti2haioia",
      "physicalSize": "1x1",
      "type": "opacity",
      "averageColor": "#000000"
    },
    {
      "mimeType": "image/x-exr",
      "bitDepth": 32,
      "name": "Roughness",
      "resolution": "2048x2048",
      "contentLength": 12569512,
      "colorSpace": "Linear",
      "uri": "Textures/Billboard/Billboard_2K_Roughness.exr",
      "asset": "ti2haioia",
      "physicalSize": "1x1",
      "type": "roughness",
      "averageColor": "#FFFFFF"
    },
    {
      "mimeType": "image/jpeg",
      "bitDepth": 8,
      "name": "Roughness",
      "resolution": "2048x2048",
      "contentLength": 844412,
      "colorSpace": "Linear",
      "uri": "Textures/Billboard/Billboard_2K_Roughness.jpg",
      "asset": "ti2haioia",
      "physicalSize": "1x1",
      "type": "roughness",
      "averageColor": "#FFFFFF"
    },
    {
      "mimeType": "image/x-exr",
      "bitDepth": 16,
      "name": "Specular",
      "resolution": "2048x2048",
      "contentLength": 34551593,
      "colorSpace": "sRGB",
      "uri": "Textures/Billboard/Billboard_2K_Specular.exr",
      "asset": "ti2haioia",
      "physicalSize": "1x1",
      "type": "specular",
      "averageColor": "#000000"
    },
    {
      "mimeType": "image/jpeg",
      "bitDepth": 8,
      "name": "Specular",
      "resolution": "2048x2048",
      "contentLength": 537103,
      "colorSpace": "sRGB",
      "uri": "Textures/Billboard/Billboard_2K_Specular.jpg",
      "asset": "ti2haioia",
      "physicalSize": "1x1",
      "type": "specular",
      "averageColor": "#000000"
    },
    {
      "mimeType": "image/x-exr",
      "bitDepth": 16,
      "name": "Translucency",
      "resolution": "2048x2048",
      "contentLength": 39751922,
      "colorSpace": "sRGB",
      "uri": "Textures/Billboard/Billboard_2K_Translucency.exr",
      "asset": "ti2haioia",
      "physicalSize": "1x1",
      "type": "translucency",
      "averageColor": "#000000"
    },
    {
      "mimeType": "image/jpeg",
      "bitDepth": 8,
      "name": "Translucency",
      "resolution": "2048x2048",
      "contentLength": 1583695,
      "colorSpace": "sRGB",
      "uri": "Textures/Billboard/Billboard_2K_Translucency.jpg",
      "asset": "ti2haioia",
      "physicalSize": "1x1",
      "type": "translucency",
      "averageColor": "#000000"
    },
    {
      "mimeType": "image/x-exr",
      "bitDepth": 32,
      "name": "AO",
      "resolution": "4096x4096",
      "contentLength": 29088272,
      "colorSpace": "sRGB",
      "uri": "Textures/Billboard/Billboard_4K_AO.exr",
      "asset": "ti2haioia",
      "physicalSize": "1x1",
      "type": "ao",
      "averageColor": "#000000"
    },
    {
      "mimeType": "image/jpeg",
      "bitDepth": 8,
      "name": "AO",
      "resolution": "4096x4096",
      "contentLength": 3282518,
      "colorSpace": "sRGB",
      "uri": "Textures/Billboard/Billboard_4K_AO.jpg",
      "asset": "ti2haioia",
      "physicalSize": "1x1",
      "type": "ao",
      "averageColor": "#000000"
    },
    {
      "mimeType": "image/x-exr",
      "bitDepth": 16,
      "name": "Albedo",
      "resolution": "4096x4096",
      "contentLength": 131185028,
      "colorSpace": "sRGB",
      "uri": "Textures/Billboard/Billboard_4K_Albedo.exr",
      "asset": "ti2haioia",
      "physicalSize": "1x1",
      "type": "albedo",
      "averageColor": "#000000"
    },
    {
      "mimeType": "image/jpeg",
      "bitDepth": 8,
      "name": "Albedo",
      "resolution": "4096x4096",
      "contentLength": 3571058,
      "colorSpace": "sRGB",
      "uri": "Textures/Billboard/Billboard_4K_Albedo.jpg",
      "asset": "ti2haioia",
      "physicalSize": "1x1",
      "type": "albedo",
      "averageColor": "#000000"
    },
    {
      "mimeType": "image/x-exr",
      "bitDepth": 32,
      "name": "Bump",
      "resolution": "4096x4096",
      "contentLength": 24577726,
      "colorSpace": "Linear",
      "uri": "Textures/Billboard/Billboard_4K_Bump.exr",
      "asset": "ti2haioia",
      "physicalSize": "1x1",
      "type": "bump",
      "averageColor": "#808080"
    },
    {
      "mimeType": "image/jpeg",
      "bitDepth": 8,
      "name": "Bump",
      "resolution": "4096x4096",
      "contentLength": 2408786,
      "colorSpace": "Linear",
      "uri": "Textures/Billboard/Billboard_4K_Bump.jpg",
      "asset": "ti2haioia",
      "physicalSize": "1x1",
      "type": "bump",
      "averageColor": "#808080"
    },
    {
      "mimeType": "image/x-exr",
      "bitDepth": 32,
      "name": "Cavity",
      "resolution": "4096x4096",
      "contentLength": 23889677,
      "colorSpace": "sRGB",
      "uri": "Textures/Billboard/Billboard_4K_Cavity.exr",
      "asset": "ti2haioia",
      "physicalSize": "1x1",
      "type": "cavity",
      "averageColor": "#000000"
    },
    {
      "mimeType": "image/jpeg",
      "bitDepth": 8,
      "name": "Cavity",
      "resolution": "4096x4096",
      "contentLength": 2729601,
      "colorSpace": "sRGB",
      "uri": "Textures/Billboard/Billboard_4K_Cavity.jpg",
      "asset": "ti2haioia",
      "physicalSize": "1x1",
      "type": "cavity",
      "averageColor": "#000000"
    },
    {
      "mimeType": "image/x-exr",
      "bitDepth": 32,
      "name": "Displacement",
      "resolution": "4096x4096",
      "contentLength": 18810237,
      "colorSpace": "Linear",
      "uri": "Textures/Billboard/Billboard_4K_Displacement.exr",
      "asset": "ti2haioia",
      "physicalSize": "1x1",
      "type": "displacement",
      "averageColor": "#000000"
    },
    {
      "mimeType": "image/jpeg",
      "bitDepth": 8,
      "name": "Displacement",
      "resolution": "4096x4096",
      "contentLength": 2413056,
      "colorSpace": "Linear",
      "uri": "Textures/Billboard/Billboard_4K_Displacement.jpg",
      "asset": "ti2haioia",
      "physicalSize": "1x1",
      "type": "displacement",
      "averageColor": "#000000"
    },
    {
      "mimeType": "image/x-exr",
      "bitDepth": 32,
      "name": "Gloss",
      "resolution": "4096x4096",
      "contentLength": 35250271,
      "colorSpace": "Linear",
      "uri": "Textures/Billboard/Billboard_4K_Gloss.exr",
      "asset": "ti2haioia",
      "physicalSize": "1x1",
      "type": "gloss",
      "averageColor": "#000000"
    },
    {
      "mimeType": "image/jpeg",
      "bitDepth": 8,
      "name": "Gloss",
      "resolution": "4096x4096",
      "contentLength": 2634268,
      "colorSpace": "Linear",
      "uri": "Textures/Billboard/Billboard_4K_Gloss.jpg",
      "asset": "ti2haioia",
      "physicalSize": "1x1",
      "type": "gloss",
      "averageColor": "#000000"
    },
    {
      "mimeType": "image/x-exr",
      "bitDepth": 16,
      "name": "Normal",
      "resolution": "4096x4096",
      "contentLength": 127869584,
      "colorSpace": "Linear",
      "uri": "Textures/Billboard/Billboard_4K_Normal.exr",
      "asset": "ti2haioia",
      "physicalSize": "1x1",
      "type": "normal",
      "averageColor": "#000000"
    },
    {
      "mimeType": "image/jpeg",
      "bitDepth": 8,
      "name": "Normal",
      "resolution": "4096x4096",
      "contentLength": 6303041,
      "colorSpace": "Linear",
      "uri": "Textures/Billboard/Billboard_4K_Normal.jpg",
      "asset": "ti2haioia",
      "physicalSize": "1x1",
      "type": "normal",
      "averageColor": "#000000"
    },
    {
      "mimeType": "image/x-exr",
      "bitDepth": 32,
      "name": "Opacity",
      "resolution": "4096x4096",
      "contentLength": 8247067,
      "colorSpace": "Linear",
      "uri": "Textures/Billboard/Billboard_4K_Opacity.exr",
      "asset": "ti2haioia",
      "physicalSize": "1x1",
      "type": "opacity",
      "averageColor": "#000000"
    },
    {
      "mimeType": "image/jpeg",
      "bitDepth": 8,
      "name": "Opacity",
      "resolution": "4096x4096",
      "contentLength": 2423271,
      "colorSpace": "Linear",
      "uri": "Textures/Billboard/Billboard_4K_Opacity.jpg",
      "asset": "ti2haioia",
      "physicalSize": "1x1",
      "type": "opacity",
      "averageColor": "#000000"
    },
    {
      "mimeType": "image/x-exr",
      "bitDepth": 32,
      "name": "Roughness",
      "resolution": "4096x4096",
      "contentLength": 30993558,
      "colorSpace": "Linear",
      "uri": "Textures/Billboard/Billboard_4K_Roughness.exr",
      "asset": "ti2haioia",
      "physicalSize": "1x1",
      "type": "roughness",
      "averageColor": "#FFFFFF"
    },
    {
      "mimeType": "image/jpeg",
      "bitDepth": 8,
      "name": "Roughness",
      "resolution": "4096x4096",
      "contentLength": 2545276,
      "colorSpace": "Linear",
      "uri": "Textures/Billboard/Billboard_4K_Roughness.jpg",
      "asset": "ti2haioia",
      "physicalSize": "1x1",
      "type": "roughness",
      "averageColor": "#FFFFFF"
    },
    {
      "mimeType": "image/x-exr",
      "bitDepth": 16,
      "name": "Specular",
      "resolution": "4096x4096",
      "contentLength": 77852224,
      "colorSpace": "sRGB",
      "uri": "Textures/Billboard/Billboard_4K_Specular.exr",
      "asset": "ti2haioia",
      "physicalSize": "1x1",
      "type": "specular",
      "averageColor": "#000000"
    },
    {
      "mimeType": "image/jpeg",
      "bitDepth": 8,
      "name": "Specular",
      "resolution": "4096x4096",
      "contentLength": 1825260,
      "colorSpace": "sRGB",
      "uri": "Textures/Billboard/Billboard_4K_Specular.jpg",
      "asset": "ti2haioia",
      "physicalSize": "1x1",
      "type": "specular",
      "averageColor": "#000000"
    },
    {
      "mimeType": "image/x-exr",
      "bitDepth": 16,
      "name": "Translucency",
      "resolution": "4096x4096",
      "contentLength": 138862332,
      "colorSpace": "sRGB",
      "uri": "Textures/Billboard/Billboard_4K_Translucency.exr",
      "asset": "ti2haioia",
      "physicalSize": "1x1",
      "type": "translucency",
      "averageColor": "#000000"
    },
    {
      "mimeType": "image/jpeg",
      "bitDepth": 8,
      "name": "Translucency",
      "resolution": "4096x4096",
      "contentLength": 4065039,
      "colorSpace": "sRGB",
      "uri": "Textures/Billboard/Billboard_4K_Translucency.jpg",
      "asset": "ti2haioia",
      "physicalSize": "1x1",
      "type": "translucency",
      "averageColor": "#000000"
    }
  ],
  "previews": {
    "images": [
      {
        "contentLength": 379561,
        "resolution": "880x440",
        "uri": "Grid_Render_Thumb.png",
        "tags": [
          "thumb"
        ]
      },
      {
        "contentLength": 1180389,
        "resolution": "1760x880",
        "uri": "Grid_Render_Thumb_Retina.png",
        "tags": [
          "retina",
          "thumb"
        ]
      },
      {
        "contentLength": 1973437,
        "resolution": "1450x816",
        "uri": "Render_Preview.png",
        "tags": [
          "preview"
        ]
      },
      {
        "contentLength": 7715136,
        "resolution": "2900x1632",
        "uri": "Render_Preview_Retina.png",
        "tags": [
          "preview",
          "retina"
        ]
      },
      {
        "contentLength": 1058,
        "resolution": "48x24",
        "uri": "JImQOJOaM5ulQ05RHVhsHF5uJnt/M4GRLUFYFFprHpKWMIOPM5WfPkdSG4OML2J0JHF+Ml1oIzhJFV1wH5CXR2x4MXeDNIqYOaiqQnh8QbrAV0tYKF91GpejP32IPUBHGkFRFmp9Kq20UYqWRG51LkxdGIkbD18AAAA5dFJOUwAkRz4PIwwEFQkbcHktXeBeeWpxSzZYOsOMgEWZWZOKx6zupdjaraXV6NheNEB5iZy985m6sP3DpBM9KbMAAAG3SURBVDjLxVPXlqMwDLUBN0zvvQYCpJEy5f+/bGCSJcmc2XNmXnb9JMu60pV0DcA/O5T8Lp7t2RWBpZ8iRI0ARii6V5LZ38MlRo9HbGWpod48SADy8rx9jpZF/2DDS6J1fcvp1aMoOUI7gilyASB7z8fbO1ched8HdRDojc5vHl1/Gzfhi7JWXDTdjaCoTXUBwH1S6KvipDfvgjDdCZTirjuuu9dhnKOYkranKhAWgJ+czxNC51Z8NkQVYDvP+uGt74dwPe6mBPalOFUrYxkHQ1snvRwzk0ciMEWAXdHgZcjHIdfcqSeiaqbhBdy/T41h5pmRJqYUkGseGdGtkq+ta6fUksGGsi+7lb7uGiu7P+a3MsDod3IhUfhzJUHoQVqXonSrT0Uwm0RaqpAniREr4Yd27EPXmWlBuUy4P1OyVR5IcJKIo3lP9FgcHZqqHyJnQkha3ukmUhmgit00pgEBcO0w9YQHjBQbVtKaWYYJEaysqspamypvXlZ15M4cRLsUHliROLYiOZbJp7jhoVjlGp01sRMyZYNnDsRRn9oWWv8+ApX7+DPPxA+mzrfDlbzH3yKD/3g+AF+GIL3UAyu4AAAAAElFTkSuQmCC",
        "tags": [
          "thumb",
          "tiny"
        ]
      },
      {
        "contentLength": 72443,
        "resolution": "880x440",
        "uri": "Grid_Render_Thumb_thumb.jpg",
        "tags": [
          "thumb",
          "jpeg"
        ]
      },
      {
        "contentLength": 229055,
        "resolution": "1760x880",
        "uri": "Grid_Render_Thumb_Retina_thumb.jpg",
        "tags": [
          "retina",
          "thumb",
          "jpeg"
        ]
      },
      {
        "contentLength": 292472,
        "resolution": "1450x816",
        "uri": "Render_Preview_preview.jpg",
        "tags": [
          "preview",
          "jpeg"
        ]
      },
      {
        "contentLength": 905826,
        "resolution": "2900x1632",
        "uri": "Render_Preview_Retina_preview.jpg",
        "tags": [
          "preview",
          "retina",
          "jpeg"
        ]
      },
      {
        "contentLength": 212091,
        "resolution": "1280x720",
        "uri": "Render_Preview_Retina_sp.jpg",
        "tags": [
          "jpeg",
          "sidepanel"
        ]
      }
    ],
    "scaleReferences": [],
    "relativeSize": "2x1"
  },
  "environment": {
    "biome": "undefined",
    "region": "Oceania"
  },
  "maps": [
    {
      "mimeType": "image/x-exr",
      "bitDepth": 32,
      "name": "AO",
      "resolution": "1024x1024",
      "contentLength": 3632612,
      "colorSpace": "sRGB",
      "uri": "Textures/Atlas/tivrfhoia_1K_AO.exr",
      "asset": "ti2haioia",
      "physicalSize": "1x1",
      "type": "ao",
      "averageColor": "#000000"
    },
    {
      "mimeType": "image/jpeg",
      "bitDepth": 8,
      "name": "AO",
      "resolution": "1024x1024",
      "contentLength": 275449,
      "colorSpace": "sRGB",
      "uri": "Textures/Atlas/tivrfhoia_1K_AO.jpg",
      "asset": "ti2haioia",
      "physicalSize": "1x1",
      "type": "ao",
      "averageColor": "#000000"
    },
    {
      "mimeType": "image/x-exr",
      "bitDepth": 16,
      "name": "Albedo",
      "resolution": "1024x1024",
      "contentLength": 10790952,
      "colorSpace": "sRGB",
      "uri": "Textures/Atlas/tivrfhoia_1K_Albedo.exr",
      "asset": "ti2haioia",
      "physicalSize": "1x1",
      "type": "albedo",
      "averageColor": "#000000"
    },
    {
      "mimeType": "image/jpeg",
      "bitDepth": 8,
      "name": "Albedo",
      "resolution": "1024x1024",
      "contentLength": 514565,
      "colorSpace": "sRGB",
      "uri": "Textures/Atlas/tivrfhoia_1K_Albedo.jpg",
      "asset": "ti2haioia",
      "physicalSize": "1x1",
      "type": "albedo",
      "averageColor": "#000000"
    },
    {
      "mimeType": "image/x-exr",
      "bitDepth": 32,
      "name": "Bump",
      "resolution": "1024x1024",
      "contentLength": 3817529,
      "colorSpace": "Linear",
      "uri": "Textures/Atlas/tivrfhoia_1K_Bump.exr",
      "asset": "ti2haioia",
      "physicalSize": "1x1",
      "type": "bump",
      "averageColor": "#808080"
    },
    {
      "mimeType": "image/jpeg",
      "bitDepth": 8,
      "name": "Bump",
      "resolution": "1024x1024",
      "contentLength": 422415,
      "colorSpace": "Linear",
      "uri": "Textures/Atlas/tivrfhoia_1K_Bump.jpg",
      "asset": "ti2haioia",
      "physicalSize": "1x1",
      "type": "bump",
      "averageColor": "#808080"
    },
    {
      "mimeType": "image/x-exr",
      "bitDepth": 32,
      "name": "Cavity",
      "resolution": "1024x1024",
      "contentLength": 3613009,
      "colorSpace": "sRGB",
      "uri": "Textures/Atlas/tivrfhoia_1K_Cavity.exr",
      "asset": "ti2haioia",
      "physicalSize": "1x1",
      "type": "cavity",
      "averageColor": "#000000"
    },
    {
      "mimeType": "image/jpeg",
      "bitDepth": 8,
      "name": "Cavity",
      "resolution": "1024x1024",
      "contentLength": 268446,
      "colorSpace": "sRGB",
      "uri": "Textures/Atlas/tivrfhoia_1K_Cavity.jpg",
      "asset": "ti2haioia",
      "physicalSize": "1x1",
      "type": "cavity",
      "averageColor": "#000000"
    },
    {
      "mimeType": "image/x-exr",
      "bitDepth": 32,
      "name": "Displacement",
      "resolution": "1024x1024",
      "contentLength": 3514037,
      "colorSpace": "Linear",
      "uri": "Textures/Atlas/tivrfhoia_1K_Displacement.exr",
      "asset": "ti2haioia",
      "physicalSize": "1x1",
      "type": "displacement",
      "averageColor": "#000000"
    },
    {
      "mimeType": "image/jpeg",
      "bitDepth": 8,
      "name": "Displacement",
      "resolution": "1024x1024",
      "contentLength": 195570,
      "colorSpace": "Linear",
      "uri": "Textures/Atlas/tivrfhoia_1K_Displacement.jpg",
      "asset": "ti2haioia",
      "physicalSize": "1x1",
      "type": "displacement",
      "averageColor": "#000000"
    },
    {
      "mimeType": "image/x-exr",
      "bitDepth": 32,
      "name": "Gloss",
      "resolution": "1024x1024",
      "contentLength": 3945202,
      "colorSpace": "Linear",
      "uri": "Textures/Atlas/tivrfhoia_1K_Gloss.exr",
      "asset": "ti2haioia",
      "physicalSize": "1x1",
      "type": "gloss",
      "averageColor": "#000000"
    },
    {
      "mimeType": "image/jpeg",
      "bitDepth": 8,
      "name": "Gloss",
      "resolution": "1024x1024",
      "contentLength": 311107,
      "colorSpace": "Linear",
      "uri": "Textures/Atlas/tivrfhoia_1K_Gloss.jpg",
      "asset": "ti2haioia",
      "physicalSize": "1x1",
      "type": "gloss",
      "averageColor": "#000000"
    },
    {
      "mimeType": "image/x-exr",
      "bitDepth": 16,
      "name": "Normal",
      "resolution": "1024x1024",
      "contentLength": 10913764,
      "colorSpace": "Linear",
      "uri": "Textures/Atlas/tivrfhoia_1K_Normal.exr",
      "asset": "ti2haioia",
      "physicalSize": "1x1",
      "type": "normal",
      "averageColor": "#000000"
    },
    {
      "mimeType": "image/jpeg",
      "bitDepth": 8,
      "name": "Normal",
      "resolution": "1024x1024",
      "contentLength": 990680,
      "colorSpace": "Linear",
      "uri": "Textures/Atlas/tivrfhoia_1K_Normal.jpg",
      "asset": "ti2haioia",
      "physicalSize": "1x1",
      "type": "normal",
      "averageColor": "#000000"
    },
    {
      "mimeType": "image/x-exr",
      "bitDepth": 32,
      "name": "Opacity",
      "resolution": "1024x1024",
      "contentLength": 1837222,
      "colorSpace": "Linear",
      "uri": "Textures/Atlas/tivrfhoia_1K_Opacity.exr",
      "asset": "ti2haioia",
      "physicalSize": "1x1",
      "type": "opacity",
      "averageColor": "#000000"
    },
    {
      "mimeType": "image/jpeg",
      "bitDepth": 8,
      "name": "Opacity",
      "resolution": "1024x1024",
      "contentLength": 443378,
      "colorSpace": "Linear",
      "uri": "Textures/Atlas/tivrfhoia_1K_Opacity.jpg",
      "asset": "ti2haioia",
      "physicalSize": "1x1",
      "type": "opacity",
      "averageColor": "#000000"
    },
    {
      "mimeType": "image/x-exr",
      "bitDepth": 32,
      "name": "Roughness",
      "resolution": "1024x1024",
      "contentLength": 3669491,
      "colorSpace": "Linear",
      "uri": "Textures/Atlas/tivrfhoia_1K_Roughness.exr",
      "asset": "ti2haioia",
      "physicalSize": "1x1",
      "type": "roughness",
      "averageColor": "#FFFFFF"
    },
    {
      "mimeType": "image/jpeg",
      "bitDepth": 8,
      "name": "Roughness",
      "resolution": "1024x1024",
      "contentLength": 300108,
      "colorSpace": "Linear",
      "uri": "Textures/Atlas/tivrfhoia_1K_Roughness.jpg",
      "asset": "ti2haioia",
      "physicalSize": "1x1",
      "type": "roughness",
      "averageColor": "#FFFFFF"
    },
    {
      "mimeType": "image/x-exr",
      "bitDepth": 16,
      "name": "Specular",
      "resolution": "1024x1024",
      "contentLength": 9059924,
      "colorSpace": "sRGB",
      "uri": "Textures/Atlas/tivrfhoia_1K_Specular.exr",
      "asset": "ti2haioia",
      "physicalSize": "1x1",
      "type": "specular",
      "averageColor": "#000000"
    },
    {
      "mimeType": "image/jpeg",
      "bitDepth": 8,
      "name": "Specular",
      "resolution": "1024x1024",
      "contentLength": 176831,
      "colorSpace": "sRGB",
      "uri": "Textures/Atlas/tivrfhoia_1K_Specular.jpg",
      "asset": "ti2haioia",
      "physicalSize": "1x1",
      "type": "specular",
      "averageColor": "#000000"
    },
    {
      "mimeType": "image/x-exr",
      "bitDepth": 16,
      "name": "Translucency",
      "resolution": "1024x1024",
      "contentLength": 11317638,
      "colorSpace": "sRGB",
      "uri": "Textures/Atlas/tivrfhoia_1K_Translucency.exr",
      "asset": "ti2haioia",
      "physicalSize": "1x1",
      "type": "translucency",
      "averageColor": "#000000"
    },
    {
      "mimeType": "image/jpeg",
      "bitDepth": 8,
      "name": "Translucency",
      "resolution": "1024x1024",
      "contentLength": 633502,
      "colorSpace": "sRGB",
      "uri": "Textures/Atlas/tivrfhoia_1K_Translucency.jpg",
      "asset": "ti2haioia",
      "physicalSize": "1x1",
      "type": "translucency",
      "averageColor": "#000000"
    },
    {
      "mimeType": "image/x-exr",
      "bitDepth": 32,
      "name": "AO",
      "resolution": "2048x2048",
      "contentLength": 13152532,
      "colorSpace": "sRGB",
      "uri": "Textures/Atlas/tivrfhoia_2K_AO.exr",
      "asset": "ti2haioia",
      "physicalSize": "1x1",
      "type": "ao",
      "averageColor": "#000000"
    },
    {
      "mimeType": "image/jpeg",
      "bitDepth": 8,
      "name": "AO",
      "resolution": "2048x2048",
      "contentLength": 794722,
      "colorSpace": "sRGB",
      "uri": "Textures/Atlas/tivrfhoia_2K_AO.jpg",
      "asset": "ti2haioia",
      "physicalSize": "1x1",
      "type": "ao",
      "averageColor": "#000000"
    },
    {
      "mimeType": "image/x-exr",
      "bitDepth": 16,
      "name": "Albedo",
      "resolution": "2048x2048",
      "contentLength": 38937238,
      "colorSpace": "sRGB",
      "uri": "Textures/Atlas/tivrfhoia_2K_Albedo.exr",
      "asset": "ti2haioia",
      "physicalSize": "1x1",
      "type": "albedo",
      "averageColor": "#000000"
    },
    {
      "mimeType": "image/jpeg",
      "bitDepth": 8,
      "name": "Albedo",
      "resolution": "2048x2048",
      "contentLength": 1345842,
      "colorSpace": "sRGB",
      "uri": "Textures/Atlas/tivrfhoia_2K_Albedo.jpg",
      "asset": "ti2haioia",
      "physicalSize": "1x1",
      "type": "albedo",
      "averageColor": "#000000"
    },
    {
      "mimeType": "image/x-exr",
      "bitDepth": 32,
      "name": "Bump",
      "resolution": "2048x2048",
      "contentLength": 13829943,
      "colorSpace": "Linear",
      "uri": "Textures/Atlas/tivrfhoia_2K_Bump.exr",
      "asset": "ti2haioia",
      "physicalSize": "1x1",
      "type": "bump",
      "averageColor": "#808080"
    },
    {
      "mimeType": "image/jpeg",
      "bitDepth": 8,
      "name": "Bump",
      "resolution": "2048x2048",
      "contentLength": 1185780,
      "colorSpace": "Linear",
      "uri": "Textures/Atlas/tivrfhoia_2K_Bump.jpg",
      "asset": "ti2haioia",
      "physicalSize": "1x1",
      "type": "bump",
      "averageColor": "#808080"
    },
    {
      "mimeType": "image/x-exr",
      "bitDepth": 32,
      "name": "Cavity",
      "resolution": "2048x2048",
      "contentLength": 13075222,
      "colorSpace": "sRGB",
      "uri": "Textures/Atlas/tivrfhoia_2K_Cavity.exr",
      "asset": "ti2haioia",
      "physicalSize": "1x1",
      "type": "cavity",
      "averageColor": "#000000"
    },
    {
      "mimeType": "image/jpeg",
      "bitDepth": 8,
      "name": "Cavity",
      "resolution": "2048x2048",
      "contentLength": 768526,
      "colorSpace": "sRGB",
      "uri": "Textures/Atlas/tivrfhoia_2K_Cavity.jpg",
      "asset": "ti2haioia",
      "physicalSize": "1x1",
      "type": "cavity",
      "averageColor": "#000000"
    },
    {
      "mimeType": "image/x-exr",
      "bitDepth": 32,
      "name": "Displacement",
      "resolution": "2048x2048",
      "contentLength": 12513494,
      "colorSpace": "Linear",
      "uri": "Textures/Atlas/tivrfhoia_2K_Displacement.exr",
      "asset": "ti2haioia",
      "physicalSize": "1x1",
      "type": "displacement",
      "averageColor": "#000000"
    },
    {
      "mimeType": "image/jpeg",
      "bitDepth": 8,
      "name": "Displacement",
      "resolution": "2048x2048",
      "contentLength": 544018,
      "colorSpace": "Linear",
      "uri": "Textures/Atlas/tivrfhoia_2K_Displacement.jpg",
      "asset": "ti2haioia",
      "physicalSize": "1x1",
      "type": "displacement",
      "averageColor": "#000000"
    },
    {
      "mimeType": "image/x-exr",
      "bitDepth": 32,
      "name": "Gloss",
      "resolution": "2048x2048",
      "contentLength": 14330722,
      "colorSpace": "Linear",
      "uri": "Textures/Atlas/tivrfhoia_2K_Gloss.exr",
      "asset": "ti2haioia",
      "physicalSize": "1x1",
      "type": "gloss",
      "averageColor": "#000000"
    },
    {
      "mimeType": "image/jpeg",
      "bitDepth": 8,
      "name": "Gloss",
      "resolution": "2048x2048",
      "contentLength": 912934,
      "colorSpace": "Linear",
      "uri": "Textures/Atlas/tivrfhoia_2K_Gloss.jpg",
      "asset": "ti2haioia",
      "physicalSize": "1x1",
      "type": "gloss",
      "averageColor": "#000000"
    },
    {
      "mimeType": "image/x-exr",
      "bitDepth": 16,
      "name": "Normal",
      "resolution": "2048x2048",
      "contentLength": 39411386,
      "colorSpace": "Linear",
      "uri": "Textures/Atlas/tivrfhoia_2K_Normal.exr",
      "asset": "ti2haioia",
      "physicalSize": "1x1",
      "type": "normal",
      "averageColor": "#000000"
    },
    {
      "mimeType": "image/jpeg",
      "bitDepth": 8,
      "name": "Normal",
      "resolution": "2048x2048",
      "contentLength": 2749257,
      "colorSpace": "Linear",
      "uri": "Textures/Atlas/tivrfhoia_2K_Normal.jpg",
      "asset": "ti2haioia",
      "physicalSize": "1x1",
      "type": "normal",
      "averageColor": "#000000"
    },
    {
      "mimeType": "image/x-exr",
      "bitDepth": 32,
      "name": "Opacity",
      "resolution": "2048x2048",
      "contentLength": 5553482,
      "colorSpace": "Linear",
      "uri": "Textures/Atlas/tivrfhoia_2K_Opacity.exr",
      "asset": "ti2haioia",
      "physicalSize": "1x1",
      "type": "opacity",
      "averageColor": "#000000"
    },
    {
      "mimeType": "image/jpeg",
      "bitDepth": 8,
      "name": "Opacity",
      "resolution": "2048x2048",
      "contentLength": 1170029,
      "colorSpace": "Linear",
      "uri": "Textures/Atlas/tivrfhoia_2K_Opacity.jpg",
      "asset": "ti2haioia",
      "physicalSize": "1x1",
      "type": "opacity",
      "averageColor": "#000000"
    },
    {
      "mimeType": "image/x-exr",
      "bitDepth": 32,
      "name": "Roughness",
      "resolution": "2048x2048",
      "contentLength": 13278667,
      "colorSpace": "Linear",
      "uri": "Textures/Atlas/tivrfhoia_2K_Roughness.exr",
      "asset": "ti2haioia",
      "physicalSize": "1x1",
      "type": "roughness",
      "averageColor": "#FFFFFF"
    },
    {
      "mimeType": "image/jpeg",
      "bitDepth": 8,
      "name": "Roughness",
      "resolution": "2048x2048",
      "contentLength": 879656,
      "colorSpace": "Linear",
      "uri": "Textures/Atlas/tivrfhoia_2K_Roughness.jpg",
      "asset": "ti2haioia",
      "physicalSize": "1x1",
      "type": "roughness",
      "averageColor": "#FFFFFF"
    },
    {
      "mimeType": "image/x-exr",
      "bitDepth": 16,
      "name": "Specular",
      "resolution": "2048x2048",
      "contentLength": 35067550,
      "colorSpace": "sRGB",
      "uri": "Textures/Atlas/tivrfhoia_2K_Specular.exr",
      "asset": "ti2haioia",
      "physicalSize": "1x1",
      "type": "specular",
      "averageColor": "#000000"
    },
    {
      "mimeType": "image/jpeg",
      "bitDepth": 8,
      "name": "Specular",
      "resolution": "2048x2048",
      "contentLength": 512855,
      "colorSpace": "sRGB",
      "uri": "Textures/Atlas/tivrfhoia_2K_Specular.jpg",
      "asset": "ti2haioia",
      "physicalSize": "1x1",
      "type": "specular",
      "averageColor": "#000000"
    },
    {
      "mimeType": "image/x-exr",
      "bitDepth": 16,
      "name": "Translucency",
      "resolution": "2048x2048",
      "contentLength": 40808477,
      "colorSpace": "sRGB",
      "uri": "Textures/Atlas/tivrfhoia_2K_Translucency.exr",
      "asset": "ti2haioia",
      "physicalSize": "1x1",
      "type": "translucency",
      "averageColor": "#000000"
    },
    {
      "mimeType": "image/jpeg",
      "bitDepth": 8,
      "name": "Translucency",
      "resolution": "2048x2048",
      "contentLength": 1681613,
      "colorSpace": "sRGB",
      "uri": "Textures/Atlas/tivrfhoia_2K_Translucency.jpg",
      "asset": "ti2haioia",
      "physicalSize": "1x1",
      "type": "translucency",
      "averageColor": "#000000"
    },
    {
      "mimeType": "image/x-exr",
      "bitDepth": 32,
      "name": "AO",
      "resolution": "4096x4096",
      "contentLength": 14035997,
      "colorSpace": "sRGB",
      "uri": "Textures/Atlas/tivrfhoia_4K_AO.exr",
      "asset": "ti2haioia",
      "physicalSize": "1x1",
      "type": "ao",
      "averageColor": "#000000"
    },
    {
      "mimeType": "image/jpeg",
      "bitDepth": 8,
      "name": "AO",
      "resolution": "4096x4096",
      "contentLength": 2433140,
      "colorSpace": "sRGB",
      "uri": "Textures/Atlas/tivrfhoia_4K_AO.jpg",
      "asset": "ti2haioia",
      "physicalSize": "1x1",
      "type": "ao",
      "averageColor": "#000000"
    },
    {
      "mimeType": "image/x-exr",
      "bitDepth": 16,
      "name": "Albedo",
      "resolution": "4096x4096",
      "contentLength": 60679086,
      "colorSpace": "sRGB",
      "uri": "Textures/Atlas/tivrfhoia_4K_Albedo.exr",
      "asset": "ti2haioia",
      "physicalSize": "1x1",
      "type": "albedo",
      "averageColor": "#000000"
    },
    {
      "mimeType": "image/jpeg",
      "bitDepth": 8,
      "name": "Albedo",
      "resolution": "4096x4096",
      "contentLength": 3655519,
      "colorSpace": "sRGB",
      "uri": "Textures/Atlas/tivrfhoia_4K_Albedo.jpg",
      "asset": "ti2haioia",
      "physicalSize": "1x1",
      "type": "albedo",
      "averageColor": "#000000"
    },
    {
      "mimeType": "image/x-exr",
      "bitDepth": 32,
      "name": "Bump",
      "resolution": "4096x4096",
      "contentLength": 48275516,
      "colorSpace": "Linear",
      "uri": "Textures/Atlas/tivrfhoia_4K_Bump.exr",
      "asset": "ti2haioia",
      "physicalSize": "1x1",
      "type": "bump",
      "averageColor": "#808080"
    },
    {
      "mimeType": "image/jpeg",
      "bitDepth": 8,
      "name": "Bump",
      "resolution": "4096x4096",
      "contentLength": 3401807,
      "colorSpace": "Linear",
      "uri": "Textures/Atlas/tivrfhoia_4K_Bump.jpg",
      "asset": "ti2haioia",
      "physicalSize": "1x1",
      "type": "bump",
      "averageColor": "#808080"
    },
    {
      "mimeType": "image/x-exr",
      "bitDepth": 32,
      "name": "Cavity",
      "resolution": "4096x4096",
      "contentLength": 13783338,
      "colorSpace": "sRGB",
      "uri": "Textures/Atlas/tivrfhoia_4K_Cavity.exr",
      "asset": "ti2haioia",
      "physicalSize": "1x1",
      "type": "cavity",
      "averageColor": "#000000"
    },
    {
      "mimeType": "image/jpeg",
      "bitDepth": 8,
      "name": "Cavity",
      "resolution": "4096x4096",
      "contentLength": 2360784,
      "colorSpace": "sRGB",
      "uri": "Textures/Atlas/tivrfhoia_4K_Cavity.jpg",
      "asset": "ti2haioia",
      "physicalSize": "1x1",
      "type": "cavity",
      "averageColor": "#000000"
    },
    {
      "mimeType": "image/x-exr",
      "bitDepth": 32,
      "name": "Displacement",
      "resolution": "4096x4096",
      "contentLength": 44122442,
      "colorSpace": "Linear",
      "uri": "Textures/Atlas/tivrfhoia_4K_Displacement.exr",
      "asset": "ti2haioia",
      "physicalSize": "1x1",
      "type": "displacement",
      "averageColor": "#000000"
    },
    {
      "mimeType": "image/jpeg",
      "bitDepth": 8,
      "name": "Displacement",
      "resolution": "4096x4096",
      "contentLength": 1829206,
      "colorSpace": "Linear",
      "uri": "Textures/Atlas/tivrfhoia_4K_Displacement.jpg",
      "asset": "ti2haioia",
      "physicalSize": "1x1",
      "type": "displacement",
      "averageColor": "#000000"
    },
    {
      "mimeType": "image/x-exr",
      "bitDepth": 32,
      "name": "Gloss",
      "resolution": "4096x4096",
      "contentLength": 20009985,
      "colorSpace": "Linear",
      "uri": "Textures/Atlas/tivrfhoia_4K_Gloss.exr",
      "asset": "ti2haioia",
      "physicalSize": "1x1",
      "type": "gloss",
      "averageColor": "#000000"
    },
    {
      "mimeType": "image/jpeg",
      "bitDepth": 8,
      "name": "Gloss",
      "resolution": "4096x4096",
      "contentLength": 2805379,
      "colorSpace": "Linear",
      "uri": "Textures/Atlas/tivrfhoia_4K_Gloss.jpg",
      "asset": "ti2haioia",
      "physicalSize": "1x1",
      "type": "gloss",
      "averageColor": "#000000"
    },
    {
      "mimeType": "image/x-exr",
      "bitDepth": 16,
      "name": "Normal",
      "resolution": "4096x4096",
      "contentLength": 144322435,
      "colorSpace": "Linear",
      "uri": "Textures/Atlas/tivrfhoia_4K_Normal.exr",
      "asset": "ti2haioia",
      "physicalSize": "1x1",
      "type": "normal",
      "averageColor": "#000000"
    },
    {
      "mimeType": "image/jpeg",
      "bitDepth": 8,
      "name": "Normal",
      "resolution": "4096x4096",
      "contentLength": 7095334,
      "colorSpace": "Linear",
      "uri": "Textures/Atlas/tivrfhoia_4K_Normal.jpg",
      "asset": "ti2haioia",
      "physicalSize": "1x1",
      "type": "normal",
      "averageColor": "#000000"
    },
    {
      "mimeType": "image/x-exr",
      "bitDepth": 32,
      "name": "Opacity",
      "resolution": "4096x4096",
      "contentLength": 6307553,
      "colorSpace": "Linear",
      "uri": "Textures/Atlas/tivrfhoia_4K_Opacity.exr",
      "asset": "ti2haioia",
      "physicalSize": "1x1",
      "type": "opacity",
      "averageColor": "#000000"
    },
    {
      "mimeType": "image/jpeg",
      "bitDepth": 8,
      "name": "Opacity",
      "resolution": "4096x4096",
      "contentLength": 2949807,
      "colorSpace": "Linear",
      "uri": "Textures/Atlas/tivrfhoia_4K_Opacity.jpg",
      "asset": "ti2haioia",
      "physicalSize": "1x1",
      "type": "opacity",
      "averageColor": "#000000"
    },
    {
      "mimeType": "image/x-exr",
      "bitDepth": 32,
      "name": "Roughness",
      "resolution": "4096x4096",
      "contentLength": 21866436,
      "colorSpace": "Linear",
      "uri": "Textures/Atlas/tivrfhoia_4K_Roughness.exr",
      "asset": "ti2haioia",
      "physicalSize": "1x1",
      "type": "roughness",
      "averageColor": "#FFFFFF"
    },
    {
      "mimeType": "image/jpeg",
      "bitDepth": 8,
      "name": "Roughness",
      "resolution": "4096x4096",
      "contentLength": 2712111,
      "colorSpace": "Linear",
      "uri": "Textures/Atlas/tivrfhoia_4K_Roughness.jpg",
      "asset": "ti2haioia",
      "physicalSize": "1x1",
      "type": "roughness",
      "averageColor": "#FFFFFF"
    },
    {
      "mimeType": "image/x-exr",
      "bitDepth": 16,
      "name": "Specular",
      "resolution": "4096x4096",
      "contentLength": 69603747,
      "colorSpace": "sRGB",
      "uri": "Textures/Atlas/tivrfhoia_4K_Specular.exr",
      "asset": "ti2haioia",
      "physicalSize": "1x1",
      "type": "specular",
      "averageColor": "#000000"
    },
    {
      "mimeType": "image/jpeg",
      "bitDepth": 8,
      "name": "Specular",
      "resolution": "4096x4096",
      "contentLength": 1723449,
      "colorSpace": "sRGB",
      "uri": "Textures/Atlas/tivrfhoia_4K_Specular.jpg",
      "asset": "ti2haioia",
      "physicalSize": "1x1",
      "type": "specular",
      "averageColor": "#000000"
    },
    {
      "mimeType": "image/x-exr",
      "bitDepth": 16,
      "name": "Translucency",
      "resolution": "4096x4096",
      "contentLength": 68002873,
      "colorSpace": "sRGB",
      "uri": "Textures/Atlas/tivrfhoia_4K_Translucency.exr",
      "asset": "ti2haioia",
      "physicalSize": "1x1",
      "type": "translucency",
      "averageColor": "#000000"
    },
    {
      "mimeType": "image/jpeg",
      "bitDepth": 8,
      "name": "Translucency",
      "resolution": "4096x4096",
      "contentLength": 4290083,
      "colorSpace": "sRGB",
      "uri": "Textures/Atlas/tivrfhoia_4K_Translucency.jpg",
      "asset": "ti2haioia",
      "physicalSize": "1x1",
      "type": "translucency",
      "averageColor": "#000000"
    }
  ],
  "json": {
    "contentLength": 56091,
    "uri": "ti2haioia.json"
  },
  "meta": [
    {
      "key": "points",
      "name": "Points",
      "value": 4
    },
    {
      "key": "useBillboardMaterial",
      "name": "UseBillboardMaterial",
      "value": true
    },
    {
      "key": "lodDistance",
      "name": "LodDistance",
      "value": [
        {
          "distance": [
            {
              "lod": 0,
              "lodDistance": 1
            },
            {
              "lod": 1,
              "lodDistance": 0.5
            },
            {
              "lod": 2,
              "lodDistance": 0.06
            },
            {
              "lod": 3,
              "lodDistance": 0.03
            }
          ],
          "variation": 1
        },
        {
          "distance": [
            {
              "lod": 0,
              "lodDistance": 1
            },
            {
              "lod": 1,
              "lodDistance": 0.5
            },
            {
              "lod": 2,
              "lodDistance": 0.06
            },
            {
              "lod": 3,
              "lodDistance": 0.03
            }
          ],
          "variation": 2
        },
        {
          "distance": [
            {
              "lod": 0,
              "lodDistance": 1
            },
            {
              "lod": 1,
              "lodDistance": 0.5
            },
            {
              "lod": 2,
              "lodDistance": 0.06
            },
            {
              "lod": 3,
              "lodDistance": 0.03
            }
          ],
          "variation": 3
        },
        {
          "distance": [
            {
              "lod": 0,
              "lodDistance": 1
            },
            {
              "lod": 1,
              "lodDistance": 0.5
            },
            {
              "lod": 2,
              "lodDistance": 0.06
            },
            {
              "lod": 3,
              "lodDistance": 0.03
            }
          ],
          "variation": 4
        },
        {
          "distance": [
            {
              "lod": 0,
              "lodDistance": 1
            },
            {
              "lod": 1,
              "lodDistance": 0.5
            },
            {
              "lod": 2,
              "lodDistance": 0.06
            },
            {
              "lod": 3,
              "lodDistance": 0.03
            }
          ],
          "variation": 5
        },
        {
          "distance": [
            {
              "lod": 0,
              "lodDistance": 1
            },
            {
              "lod": 1,
              "lodDistance": 0.5
            },
            {
              "lod": 2,
              "lodDistance": 0.06
            },
            {
              "lod": 3,
              "lodDistance": 0.03
            }
          ],
          "variation": 6
        },
        {
          "distance": [
            {
              "lod": 0,
              "lodDistance": 1
            },
            {
              "lod": 1,
              "lodDistance": 0.5
            },
            {
              "lod": 2,
              "lodDistance": 0.06
            },
            {
              "lod": 3,
              "lodDistance": 0.03
            }
          ],
          "variation": 7
        }
      ]
    }
  ],
  "references": [],
  "categories": [
    "3dplant",
    "plants",
    "weed"
  ],
  "version": 2,
  "referencePreviews": {
    "models": [
      {
        "mimeType": "application/x-abc",
        "lod": 0,
        "contentLength": 52096,
        "uri": "",
        "variation": 1,
        "type": "lod"
      },
      {
        "mimeType": "application/x-fbx",
        "lod": 0,
        "contentLength": 52784,
        "uri": "",
        "variation": 1,
        "type": "lod"
      },
      {
        "mimeType": "application/x-abc",
        "lod": 1,
        "contentLength": 23064,
        "uri": "",
        "variation": 1,
        "type": "lod"
      },
      {
        "mimeType": "application/x-fbx",
        "lod": 1,
        "contentLength": 36208,
        "uri": "",
        "variation": 1,
        "type": "lod"
      },
      {
        "mimeType": "application/x-abc",
        "lod": 0,
        "contentLength": 39244,
        "uri": "",
        "variation": 2,
        "type": "lod"
      },
      {
        "mimeType": "application/x-fbx",
        "lod": 0,
        "contentLength": 44784,
        "uri": "",
        "variation": 2,
        "type": "lod"
      },
      {
        "mimeType": "application/x-abc",
        "lod": 1,
        "contentLength": 17472,
        "uri": "",
        "variation": 2,
        "type": "lod"
      },
      {
        "mimeType": "application/x-fbx",
        "lod": 1,
        "contentLength": 32736,
        "uri": "",
        "variation": 2,
        "type": "lod"
      },
      {
        "mimeType": "application/x-abc",
        "lod": 0,
        "contentLength": 26420,
        "uri": "",
        "variation": 3,
        "type": "lod"
      },
      {
        "mimeType": "application/x-fbx",
        "lod": 0,
        "contentLength": 36736,
        "uri": "",
        "variation": 3,
        "type": "lod"
      },
      {
        "mimeType": "application/x-abc",
        "lod": 1,
        "contentLength": 12384,
        "uri": "",
        "variation": 3,
        "type": "lod"
      },
      {
        "mimeType": "application/x-fbx",
        "lod": 1,
        "contentLength": 32336,
        "uri": "",
        "variation": 3,
        "type": "lod"
      },
      {
        "mimeType": "application/x-abc",
        "lod": 0,
        "contentLength": 23760,
        "uri": "",
        "variation": 4,
        "type": "lod"
      },
      {
        "mimeType": "application/x-fbx",
        "lod": 0,
        "contentLength": 34928,
        "uri": "",
        "variation": 4,
        "type": "lod"
      },
      {
        "mimeType": "application/x-abc",
        "lod": 1,
        "contentLength": 11620,
        "uri": "",
        "variation": 4,
        "type": "lod"
      },
      {
        "mimeType": "application/x-fbx",
        "lod": 1,
        "contentLength": 31296,
        "uri": "",
        "variation": 4,
        "type": "lod"
      },
      {
        "mimeType": "application/x-abc",
        "lod": 0,
        "contentLength": 13608,
        "uri": "",
        "variation": 5,
        "type": "lod"
      },
      {
        "mimeType": "application/x-fbx",
        "lod": 0,
        "contentLength": 31376,
        "uri": "",
        "variation": 5,
        "type": "lod"
      },
      {
        "mimeType": "application/x-abc",
        "lod": 1,
        "contentLength": 8356,
        "uri": "",
        "variation": 5,
        "type": "lod"
      },
      {
        "mimeType": "application/x-fbx",
        "lod": 1,
        "contentLength": 29456,
        "uri": "",
        "variation": 5,
        "type": "lod"
      },
      {
        "mimeType": "application/x-abc",
        "lod": 0,
        "contentLength": 12376,
        "uri": "",
        "variation": 6,
        "type": "lod"
      },
      {
        "mimeType": "application/x-fbx",
        "lod": 0,
        "contentLength": 32832,
        "uri": "",
        "variation": 6,
        "type": "lod"
      },
      {
        "mimeType": "application/x-abc",
        "lod": 1,
        "contentLength": 7952,
        "uri": "",
        "variation": 6,
        "type": "lod"
      },
      {
        "mimeType": "application/x-fbx",
        "lod": 1,
        "contentLength": 28688,
        "uri": "",
        "variation": 6,
        "type": "lod"
      },
      {
        "mimeType": "application/x-abc",
        "lod": 0,
        "contentLength": 15512,
        "uri": "",
        "variation": 7,
        "type": "lod"
      },
      {
        "mimeType": "application/x-fbx",
        "lod": 0,
        "contentLength": 33296,
        "uri": "",
        "variation": 7,
        "type": "lod"
      },
      {
        "mimeType": "application/x-abc",
        "lod": 1,
        "contentLength": 12016,
        "uri": "",
        "variation": 7,
        "type": "lod"
      },
      {
        "mimeType": "application/x-fbx",
        "lod": 1,
        "contentLength": 31184,
        "uri": "",
        "variation": 7,
        "type": "lod"
      }
    ],
    "maps": [
      {
        "mimeType": "image/jpeg",
        "resolution": "1024x1024",
        "contentLength": 275449,
        "type": "ao",
        "uri": "tivrfhoia_1K_AO.jpg"
      },
      {
        "mimeType": "image/jpeg",
        "resolution": "1024x1024",
        "contentLength": 514565,
        "type": "albedo",
        "uri": "tivrfhoia_1K_Albedo.jpg"
      },
      {
        "mimeType": "image/jpeg",
        "resolution": "1024x1024",
        "contentLength": 422415,
        "type": "bump",
        "uri": "tivrfhoia_1K_Bump.jpg"
      },
      {
        "mimeType": "image/jpeg",
        "resolution": "1024x1024",
        "contentLength": 268446,
        "type": "cavity",
        "uri": "tivrfhoia_1K_Cavity.jpg"
      },
      {
        "mimeType": "image/jpeg",
        "resolution": "1024x1024",
        "contentLength": 195570,
        "type": "displacement",
        "uri": "tivrfhoia_1K_Displacement.jpg"
      },
      {
        "mimeType": "image/jpeg",
        "resolution": "1024x1024",
        "contentLength": 311107,
        "type": "gloss",
        "uri": "tivrfhoia_1K_Gloss.jpg"
      },
      {
        "mimeType": "image/jpeg",
        "resolution": "1024x1024",
        "contentLength": 990680,
        "type": "normal",
        "uri": "tivrfhoia_1K_Normal.jpg"
      },
      {
        "mimeType": "image/jpeg",
        "resolution": "1024x1024",
        "contentLength": 443378,
        "type": "opacity",
        "uri": "tivrfhoia_1K_Opacity.jpg"
      },
      {
        "mimeType": "image/jpeg",
        "resolution": "1024x1024",
        "contentLength": 300108,
        "type": "roughness",
        "uri": "tivrfhoia_1K_Roughness.jpg"
      },
      {
        "mimeType": "image/jpeg",
        "resolution": "1024x1024",
        "contentLength": 176831,
        "type": "specular",
        "uri": "tivrfhoia_1K_Specular.jpg"
      },
      {
        "mimeType": "image/jpeg",
        "resolution": "1024x1024",
        "contentLength": 633502,
        "type": "translucency",
        "uri": "tivrfhoia_1K_Translucency.jpg"
      }
    ]
  },
  "properties": [],
  "averageColor": "#000000",
  "points": 4,
  "assetCategories": {
    "3D plant": {
      "weed": {
        "urban": {},
        "meadow": {},
        "forest": {}
      },
      "flowering plant": {
        "flowerhead": {}
      }
    }
  },
  "semanticTags": {
    "city": [],
    "theme": [
      "lawns",
      " roadsides",
      " gardens",
      " disturbed areas"
    ],
    "name": "Funnel Weed",
    "subject_matter": "nature",
    "industry": [
      "archviz",
      "games",
      "VFX"
    ],
    "contains": [
      "whole plants",
      "leaves",
      "clumps",
      "buttonweed"
    ],
    "locations": {
      "Oceania": {
        "Australia": {}
      }
    },
    "descriptive": [
      "variations",
      " healthy",
      " growing",
      " flowering"
    ],
    "environment": [
      "tropical jungle biome"
    ],
    "interior_exterior": [],
    "state": [
      "old"
    ],
    "latin_name": "cotula turbinata",
    "architectural_style": {},
    "3d_mesh": "Open",
    "resolution": 4096,
    "asset_type": "3D plant",
    "orientation": [],
    "maxSize": "",
    "minSize": ""
  },
  "uasset": [
    {
      "type": "model",
      "ueVersion": "5.0.0",
      "tier": 1,
      "mimeType": "uasset",
      "uri": "UAsset/Tier1/S_Funnel_Weed_ti2haioia_Var1_lod0.uasset"
    },
    {
      "type": "model",
      "ueVersion": "5.0.0",
      "tier": 1,
      "mimeType": "uasset",
      "uri": "UAsset/Tier1/S_Funnel_Weed_ti2haioia_Var2_lod0.uasset"
    },
    {
      "type": "model",
      "ueVersion": "5.0.0",
      "tier": 1,
      "mimeType": "uasset",
      "uri": "UAsset/Tier1/S_Funnel_Weed_ti2haioia_Var3_lod0.uasset"
    },
    {
      "type": "model",
      "ueVersion": "5.0.0",
      "tier": 1,
      "mimeType": "uasset",
      "uri": "UAsset/Tier1/S_Funnel_Weed_ti2haioia_Var4_lod0.uasset"
    },
    {
      "type": "model",
      "ueVersion": "5.0.0",
      "tier": 1,
      "mimeType": "uasset",
      "uri": "UAsset/Tier1/S_Funnel_Weed_ti2haioia_Var5_lod0.uasset"
    },
    {
      "type": "model",
      "ueVersion": "5.0.0",
      "tier": 1,
      "mimeType": "uasset",
      "uri": "UAsset/Tier1/S_Funnel_Weed_ti2haioia_Var6_lod0.uasset"
    },
    {
      "type": "model",
      "ueVersion": "5.0.0",
      "tier": 1,
      "mimeType": "uasset",
      "uri": "UAsset/Tier1/S_Funnel_Weed_ti2haioia_Var7_lod0.uasset"
    },
    {
      "type": "material",
      "ueVersion": "5.0.0",
      "tier": 1,
      "mimeType": "uasset",
      "uri": "UAsset/Tier1/MI_Funnel_Weed_ti2haioia_4K.uasset"
    },
    {
      "type": "material",
      "ueVersion": "5.0.0",
      "tier": 1,
      "mimeType": "uasset",
      "uri": "UAsset/Tier1/MI_Funnel_Weed_ti2haioia_Billboard_4K.uasset"
    },
    {
      "type": "map",
      "ueVersion": "5.0.0",
      "tier": 1,
      "mimeType": "uasset",
      "uri": "UAsset/Tier1/T_FunnelWeed_ti2haioia_4K_ART.uasset",
      "sub-type": "ort"
    },
    {
      "type": "map",
      "ueVersion": "5.0.0",
      "tier": 1,
      "mimeType": "uasset",
      "uri": "UAsset/Tier1/T_Funnel_Weed_ti2haioia_4K_D.uasset",
      "sub-type": "albedo"
    },
    {
      "type": "map",
      "ueVersion": "5.0.0",
      "tier": 1,
      "mimeType": "uasset",
      "uri": "UAsset/Tier1/T_Funnel_Weed_ti2haioia_4K_N.uasset",
      "sub-type": "normal"
    },
    {
      "type": "map",
      "ueVersion": "5.0.0",
      "tier": 1,
      "mimeType": "uasset",
      "uri": "UAsset/Tier1/T_FunnelWeed_ti2haioia_4K_billboard_ART.uasset",
      "sub-type": "packtexture"
    },
    {
      "type": "map",
      "ueVersion": "5.0.0",
      "tier": 1,
      "mimeType": "uasset",
      "uri": "UAsset/Tier1/T_Funnel_Weed_ti2haioia_Billboard_D.uasset",
      "sub-type": "albedo"
    },
    {
      "type": "map",
      "ueVersion": "5.0.0",
      "tier": 1,
      "mimeType": "uasset",
      "uri": "UAsset/Tier1/T_Funnel_Weed_ti2haioia_Billboard_N.uasset",
      "sub-type": "normal"
    },
    {
      "type": "foliage",
      "ueVersion": "5.0.0",
      "tier": 1,
      "mimeType": "uasset",
      "uri": "UAsset/Tier1/Foliage/FT_Funnel_Weed_ti2haioia_Var1_lod0.uasset"
    },
    {
      "type": "foliage",
      "ueVersion": "5.0.0",
      "tier": 1,
      "mimeType": "uasset",
      "uri": "UAsset/Tier1/Foliage/FT_Funnel_Weed_ti2haioia_Var2_lod0.uasset"
    },
    {
      "type": "foliage",
      "ueVersion": "5.0.0",
      "tier": 1,
      "mimeType": "uasset",
      "uri": "UAsset/Tier1/Foliage/FT_Funnel_Weed_ti2haioia_Var3_lod0.uasset"
    },
    {
      "type": "foliage",
      "ueVersion": "5.0.0",
      "tier": 1,
      "mimeType": "uasset",
      "uri": "UAsset/Tier1/Foliage/FT_Funnel_Weed_ti2haioia_Var4_lod0.uasset"
    },
    {
      "type": "foliage",
      "ueVersion": "5.0.0",
      "tier": 1,
      "mimeType": "uasset",
      "uri": "UAsset/Tier1/Foliage/FT_Funnel_Weed_ti2haioia_Var5_lod0.uasset"
    },
    {
      "type": "foliage",
      "ueVersion": "5.0.0",
      "tier": 1,
      "mimeType": "uasset",
      "uri": "UAsset/Tier1/Foliage/FT_Funnel_Weed_ti2haioia_Var6_lod0.uasset"
    },
    {
      "type": "foliage",
      "ueVersion": "5.0.0",
      "tier": 1,
      "mimeType": "uasset",
      "uri": "UAsset/Tier1/Foliage/FT_Funnel_Weed_ti2haioia_Var7_lod0.uasset"
    },
    {
      "type": "meta",
      "ueVersion": "5.0.0",
      "tier": 1,
      "mimeType": "json",
      "uri": "UAsset/Tier1/ti2haioia_1.json"
    },
    {
      "type": "model",
      "ueVersion": "5.0.0",
      "tier": 2,
      "mimeType": "uasset",
      "uri": "UAsset/Tier2/S_Funnel_Weed_ti2haioia_Var1_lod1.uasset"
    },
    {
      "type": "model",
      "ueVersion": "5.0.0",
      "tier": 2,
      "mimeType": "uasset",
      "uri": "UAsset/Tier2/S_Funnel_Weed_ti2haioia_Var2_lod1.uasset"
    },
    {
      "type": "model",
      "ueVersion": "5.0.0",
      "tier": 2,
      "mimeType": "uasset",
      "uri": "UAsset/Tier2/S_Funnel_Weed_ti2haioia_Var3_lod1.uasset"
    },
    {
      "type": "model",
      "ueVersion": "5.0.0",
      "tier": 2,
      "mimeType": "uasset",
      "uri": "UAsset/Tier2/S_Funnel_Weed_ti2haioia_Var4_lod1.uasset"
    },
    {
      "type": "model",
      "ueVersion": "5.0.0",
      "tier": 2,
      "mimeType": "uasset",
      "uri": "UAsset/Tier2/S_Funnel_Weed_ti2haioia_Var5_lod1.uasset"
    },
    {
      "type": "model",
      "ueVersion": "5.0.0",
      "tier": 2,
      "mimeType": "uasset",
      "uri": "UAsset/Tier2/S_Funnel_Weed_ti2haioia_Var6_lod1.uasset"
    },
    {
      "type": "model",
      "ueVersion": "5.0.0",
      "tier": 2,
      "mimeType": "uasset",
      "uri": "UAsset/Tier2/S_Funnel_Weed_ti2haioia_Var7_lod1.uasset"
    },
    {
      "type": "material",
      "ueVersion": "5.0.0",
      "tier": 2,
      "mimeType": "uasset",
      "uri": "UAsset/Tier2/MI_Funnel_Weed_ti2haioia_2K.uasset"
    },
    {
      "type": "material",
      "ueVersion": "5.0.0",
      "tier": 2,
      "mimeType": "uasset",
      "uri": "UAsset/Tier2/MI_Funnel_Weed_ti2haioia_Billboard_2K.uasset"
    },
    {
      "type": "map",
      "ueVersion": "5.0.0",
      "tier": 2,
      "mimeType": "uasset",
      "uri": "UAsset/Tier2/T_FunnelWeed_ti2haioia_2K_ART.uasset",
      "sub-type": "ort"
    },
    {
      "type": "map",
      "ueVersion": "5.0.0",
      "tier": 2,
      "mimeType": "uasset",
      "uri": "UAsset/Tier2/T_Funnel_Weed_ti2haioia_2K_D.uasset",
      "sub-type": "albedo"
    },
    {
      "type": "map",
      "ueVersion": "5.0.0",
      "tier": 2,
      "mimeType": "uasset",
      "uri": "UAsset/Tier2/T_Funnel_Weed_ti2haioia_2K_N.uasset",
      "sub-type": "normal"
    },
    {
      "type": "map",
      "ueVersion": "5.0.0",
      "tier": 2,
      "mimeType": "uasset",
      "uri": "UAsset/Tier2/T_FunnelWeed_ti2haioia_2K_billboard_ART.uasset",
      "sub-type": "packtexture"
    },
    {
      "type": "map",
      "ueVersion": "5.0.0",
      "tier": 2,
      "mimeType": "uasset",
      "uri": "UAsset/Tier2/T_Funnel_Weed_ti2haioia_Billboard_D.uasset",
      "sub-type": "albedo"
    },
    {
      "type": "map",
      "ueVersion": "5.0.0",
      "tier": 2,
      "mimeType": "uasset",
      "uri": "UAsset/Tier2/T_Funnel_Weed_ti2haioia_Billboard_N.uasset",
      "sub-type": "normal"
    },
    {
      "type": "foliage",
      "ueVersion": "5.0.0",
      "tier": 2,
      "mimeType": "uasset",
      "uri": "UAsset/Tier2/Foliage/FT_Funnel_Weed_ti2haioia_Var1_lod1.uasset"
    },
    {
      "type": "foliage",
      "ueVersion": "5.0.0",
      "tier": 2,
      "mimeType": "uasset",
      "uri": "UAsset/Tier2/Foliage/FT_Funnel_Weed_ti2haioia_Var2_lod1.uasset"
    },
    {
      "type": "foliage",
      "ueVersion": "5.0.0",
      "tier": 2,
      "mimeType": "uasset",
      "uri": "UAsset/Tier2/Foliage/FT_Funnel_Weed_ti2haioia_Var3_lod1.uasset"
    },
    {
      "type": "foliage",
      "ueVersion": "5.0.0",
      "tier": 2,
      "mimeType": "uasset",
      "uri": "UAsset/Tier2/Foliage/FT_Funnel_Weed_ti2haioia_Var4_lod1.uasset"
    },
    {
      "type": "foliage",
      "ueVersion": "5.0.0",
      "tier": 2,
      "mimeType": "uasset",
      "uri": "UAsset/Tier2/Foliage/FT_Funnel_Weed_ti2haioia_Var5_lod1.uasset"
    },
    {
      "type": "foliage",
      "ueVersion": "5.0.0",
      "tier": 2,
      "mimeType": "uasset",
      "uri": "UAsset/Tier2/Foliage/FT_Funnel_Weed_ti2haioia_Var6_lod1.uasset"
    },
    {
      "type": "foliage",
      "ueVersion": "5.0.0",
      "tier": 2,
      "mimeType": "uasset",
      "uri": "UAsset/Tier2/Foliage/FT_Funnel_Weed_ti2haioia_Var7_lod1.uasset"
    },
    {
      "type": "meta",
      "ueVersion": "5.0.0",
      "tier": 2,
      "mimeType": "json",
      "uri": "UAsset/Tier2/ti2haioia_2.json"
    },
    {
      "type": "model",
      "ueVersion": "5.0.0",
      "tier": 3,
      "mimeType": "uasset",
      "uri": "UAsset/Tier3/S_Funnel_Weed_ti2haioia_Var1_lod3.uasset"
    },
    {
      "type": "model",
      "ueVersion": "5.0.0",
      "tier": 3,
      "mimeType": "uasset",
      "uri": "UAsset/Tier3/S_Funnel_Weed_ti2haioia_Var2_lod3.uasset"
    },
    {
      "type": "model",
      "ueVersion": "5.0.0",
      "tier": 3,
      "mimeType": "uasset",
      "uri": "UAsset/Tier3/S_Funnel_Weed_ti2haioia_Var3_lod3.uasset"
    },
    {
      "type": "model",
      "ueVersion": "5.0.0",
      "tier": 3,
      "mimeType": "uasset",
      "uri": "UAsset/Tier3/S_Funnel_Weed_ti2haioia_Var4_lod3.uasset"
    },
    {
      "type": "model",
      "ueVersion": "5.0.0",
      "tier": 3,
      "mimeType": "uasset",
      "uri": "UAsset/Tier3/S_Funnel_Weed_ti2haioia_Var5_lod3.uasset"
    },
    {
      "type": "model",
      "ueVersion": "5.0.0",
      "tier": 3,
      "mimeType": "uasset",
      "uri": "UAsset/Tier3/S_Funnel_Weed_ti2haioia_Var6_lod3.uasset"
    },
    {
      "type": "model",
      "ueVersion": "5.0.0",
      "tier": 3,
      "mimeType": "uasset",
      "uri": "UAsset/Tier3/S_Funnel_Weed_ti2haioia_Var7_lod3.uasset"
    },
    {
      "type": "material",
      "ueVersion": "5.0.0",
      "tier": 3,
      "mimeType": "uasset",
      "uri": "UAsset/Tier3/MI_Funnel_Weed_ti2haioia_1K.uasset"
    },
    {
      "type": "material",
      "ueVersion": "5.0.0",
      "tier": 3,
      "mimeType": "uasset",
      "uri": "UAsset/Tier3/MI_Funnel_Weed_ti2haioia_Billboard_1K.uasset"
    },
    {
      "type": "map",
      "ueVersion": "5.0.0",
      "tier": 3,
      "mimeType": "uasset",
      "uri": "UAsset/Tier3/T_FunnelWeed_ti2haioia_1K_ART.uasset",
      "sub-type": "ort"
    },
    {
      "type": "map",
      "ueVersion": "5.0.0",
      "tier": 3,
      "mimeType": "uasset",
      "uri": "UAsset/Tier3/T_Funnel_Weed_ti2haioia_1K_D.uasset",
      "sub-type": "albedo"
    },
    {
      "type": "map",
      "ueVersion": "5.0.0",
      "tier": 3,
      "mimeType": "uasset",
      "uri": "UAsset/Tier3/T_Funnel_Weed_ti2haioia_1K_N.uasset",
      "sub-type": "normal"
    },
    {
      "type": "map",
      "ueVersion": "5.0.0",
      "tier": 3,
      "mimeType": "uasset",
      "uri": "UAsset/Tier3/T_FunnelWeed_ti2haioia_1K_billboard_ART.uasset",
      "sub-type": "packtexture"
    },
    {
      "type": "map",
      "ueVersion": "5.0.0",
      "tier": 3,
      "mimeType": "uasset",
      "uri": "UAsset/Tier3/T_Funnel_Weed_ti2haioia_Billboard_D.uasset",
      "sub-type": "albedo"
    },
    {
      "type": "map",
      "ueVersion": "5.0.0",
      "tier": 3,
      "mimeType": "uasset",
      "uri": "UAsset/Tier3/T_Funnel_Weed_ti2haioia_Billboard_N.uasset",
      "sub-type": "normal"
    },
    {
      "type": "foliage",
      "ueVersion": "5.0.0",
      "tier": 3,
      "mimeType": "uasset",
      "uri": "UAsset/Tier3/Foliage/FT_Funnel_Weed_ti2haioia_Var1_lod3.uasset"
    },
    {
      "type": "foliage",
      "ueVersion": "5.0.0",
      "tier": 3,
      "mimeType": "uasset",
      "uri": "UAsset/Tier3/Foliage/FT_Funnel_Weed_ti2haioia_Var2_lod3.uasset"
    },
    {
      "type": "foliage",
      "ueVersion": "5.0.0",
      "tier": 3,
      "mimeType": "uasset",
      "uri": "UAsset/Tier3/Foliage/FT_Funnel_Weed_ti2haioia_Var3_lod3.uasset"
    },
    {
      "type": "foliage",
      "ueVersion": "5.0.0",
      "tier": 3,
      "mimeType": "uasset",
      "uri": "UAsset/Tier3/Foliage/FT_Funnel_Weed_ti2haioia_Var4_lod3.uasset"
    },
    {
      "type": "foliage",
      "ueVersion": "5.0.0",
      "tier": 3,
      "mimeType": "uasset",
      "uri": "UAsset/Tier3/Foliage/FT_Funnel_Weed_ti2haioia_Var5_lod3.uasset"
    },
    {
      "type": "foliage",
      "ueVersion": "5.0.0",
      "tier": 3,
      "mimeType": "uasset",
      "uri": "UAsset/Tier3/Foliage/FT_Funnel_Weed_ti2haioia_Var6_lod3.uasset"
    },
    {
      "type": "foliage",
      "ueVersion": "5.0.0",
      "tier": 3,
      "mimeType": "uasset",
      "uri": "UAsset/Tier3/Foliage/FT_Funnel_Weed_ti2haioia_Var7_lod3.uasset"
    },
    {
      "type": "meta",
      "ueVersion": "5.0.0",
      "tier": 3,
      "mimeType": "json",
      "uri": "UAsset/Tier3/ti2haioia_3.json"
    },
    {
      "type": "model",
      "ueVersion": "5.0.0",
      "tier": 4,
      "mimeType": "uasset",
      "uri": "UAsset/Tier4/S_Funnel_Weed_ti2haioia_Var1_lod3.uasset"
    },
    {
      "type": "material",
      "ueVersion": "5.0.0",
      "tier": 4,
      "mimeType": "uasset",
      "uri": "UAsset/Tier4/MI_Funnel_Weed_ti2haioia_1K.uasset"
    },
    {
      "type": "map",
      "ueVersion": "5.0.0",
      "tier": 4,
      "mimeType": "uasset",
      "uri": "UAsset/Tier4/T_Funnel_Weed_ti2haioia_1K_Billboard_D.uasset",
      "sub-type": "albedo"
    },
    {
      "type": "map",
      "ueVersion": "5.0.0",
      "tier": 4,
      "mimeType": "uasset",
      "uri": "UAsset/Tier4/T_Funnel_Weed_ti2haioia_1K_Billboard_N.uasset",
      "sub-type": "normal"
    },
    {
      "type": "meta",
      "ueVersion": "5.0.0",
      "tier": 4,
      "mimeType": "json",
      "uri": "UAsset/Tier4/ti2haioia_4.json"
    }
  ],
  "comp_version": 1,
  "revised": false,
  "id": "ti2haioia",
  "physicalSize": null
}